PyDunk/__init__.py
PyDunk/__main__.py
PyDunk/launch.py
PyDunk/auth/__init__.py
PyDunk/auth/models.py
PyDunk/auth/session.py
PyDunk/auth/utils.py
PyDunk/utils/__init__.py
PyDunk/utils/anisette.py
PyDunk/xcode/__init__.py
PyDunk/xcode/auth.py
PyDunk/xcode/session.py
PyDunk/xcode/models/__init__.py
PyDunk/xcode/models/account.py
pydunk-0.0.2.dist-info/METADATA
pydunk-0.0.2.dist-info/WHEEL
pydunk-0.0.2.dist-info/entry_points.txt
pydunk-0.0.2.dist-info/licenses/LICENSE
pydunk-0.0.2.dist-info/RECORD
